chipwhisperer/__init__.py
chipwhisperer/logging.py
chipwhisperer/py.typed
chipwhisperer/analyzer/__init__.py
chipwhisperer/analyzer/attacks/__init__.py
chipwhisperer/analyzer/attacks/_base.py
chipwhisperer/analyzer/attacks/_channel_estimate_attack.py
chipwhisperer/analyzer/attacks/_stats.py
chipwhisperer/analyzer/attacks/algorithmsbase.py
chipwhisperer/analyzer/attacks/attack_mix_columns.py
chipwhisperer/analyzer/attacks/coefficient_vs_trace_number.py
chipwhisperer/analyzer/attacks/cpa.py
chipwhisperer/analyzer/attacks/cpa_new.py
chipwhisperer/analyzer/attacks/profiling.py
chipwhisperer/analyzer/attacks/snr.py
chipwhisperer/analyzer/attacks/cpa_algorithms/__init__.py
chipwhisperer/analyzer/attacks/cpa_algorithms/bayesian.py
chipwhisperer/analyzer/attacks/cpa_algorithms/progressive.py
chipwhisperer/analyzer/attacks/cpa_algorithms/progressive_caccel.py
chipwhisperer/analyzer/attacks/cpa_algorithms/simpleloop.py
chipwhisperer/analyzer/attacks/cpa_algorithms/c_accel/AESModels.cpp
chipwhisperer/analyzer/attacks/cpa_algorithms/c_accel/AESModels.h
chipwhisperer/analyzer/attacks/cpa_algorithms/c_accel/CPAProgressive.cpp
chipwhisperer/analyzer/attacks/cpa_algorithms/c_accel/CPAProgressive.h
chipwhisperer/analyzer/attacks/cpa_algorithms/c_accel/Makefile
chipwhisperer/analyzer/attacks/cpa_algorithms/c_accel/libcpa.dll
chipwhisperer/analyzer/attacks/cpa_algorithms/c_accel/libcpa_x64.dll
chipwhisperer/analyzer/attacks/cpa_algorithms/c_accel/make_winvs.bat
chipwhisperer/analyzer/attacks/models/AES128_8bit.py
chipwhisperer/analyzer/attacks/models/AES256_8bit.py
chipwhisperer/analyzer/attacks/models/DES.py
chipwhisperer/analyzer/attacks/models/XOR.py
chipwhisperer/analyzer/attacks/models/__init__.py
chipwhisperer/analyzer/attacks/models/base.py
chipwhisperer/analyzer/attacks/models/aes/__init__.py
chipwhisperer/analyzer/attacks/models/aes/funcs.py
chipwhisperer/analyzer/attacks/models/aes/key_schedule.py
chipwhisperer/analyzer/attacks/profiling_algorithms/__init__.py
chipwhisperer-5.7.0.dist-info/LICENSE.txt
chipwhisperer-5.7.0.dist-info/METADATA
chipwhisperer-5.7.0.dist-info/WHEEL
chipwhisperer-5.7.0.dist-info/top_level.txt
chipwhisperer-5.7.0.dist-info/RECORD
