Metadata-Version: 2.2
Name: chipwhisperer
Version: 5.7.0
Summary: ChipWhisperer Side-Channel Analysis Tool
Author-email: Colin O'Flynn <coflynn@newae.com>
License: Certain files in this project may have specific licenses or copyright
Project-URL: Homepage, https://www.chipwhisperer.com
Project-URL: Documentation, https://chipwhisperer.readthedocs.io/en/latest/
Project-URL: Repository, https://github.com/newaetech/chipwhisperer
Requires-Python: >=3.9
License-File: LICENSE.txt
Requires-Dist: configobj
Requires-Dist: pyserial
Requires-Dist: numpy<=1.26.4
Requires-Dist: libusb1
Requires-Dist: ECpy
Requires-Dist: fastdtw
Requires-Dist: Cython
Requires-Dist: tqdm
Requires-Dist: libusb1
Provides-Extra: trace
Requires-Dist: software; extra == "trace"
